{
    "version": 2,
    "map": {
        "center": {
            "x": 3.5384114583333455,
            "y": 14.843882567890963,
            "crs": "EPSG:4326"
        },
        "maxExtent": [
            -20037508.34,
            -20037508.34,
            20037508.34,
            20037508.34
        ],
        "projection": "EPSG:900913",
        "units": "m",
        "zoom": 3,
        "mapOptions": {},
        "layers": [
            {
                "id": "osm:osm__0",
                "format": "image/jpeg",
                "thumbURL": "assets/img/osm-bright.jpg",
                "group": "background",
                "source": "osm",
                "name": "osm:osm",
                "opacity": 1,
                "title": "OSM Bright",
                "type": "wms",
                "url": [
                    "https://maps1.geosolutionsgroup.com/geoserver/wms",
                    "https://maps2.geosolutionsgroup.com/geoserver/wms",
                    "https://maps3.geosolutionsgroup.com/geoserver/wms",
                    "https://maps4.geosolutionsgroup.com/geoserver/wms",
                    "https://maps5.geosolutionsgroup.com/geoserver/wms",
                    "https://maps6.geosolutionsgroup.com/geoserver/wms"
                ],
                "visibility": true,
                "singleTile": false,
                "dimensions": [],
                "hideLoading": false,
                "handleClickOnLayer": false,
                "useForElevation": false,
                "hidden": false,
                "credits": {
                    "title": "OSM Bright | Rendering <a href=\"https://www.geo-solutions.it/\">GeoSolutions</a> | Data © <a href=\"http://www.openstreetmap.org/\">OpenStreetMap</a> contributors, <a href=\"http://www.openstreetmap.org/copyright\">ODbL</a>"
                }
            },
            {
                "id": "osm:osm_simple_dark__1",
                "format": "image/jpeg",
                "thumbURL": "assets/img/osm-simple-dark.jpg",
                "group": "background",
                "source": "osm_simple_dark",
                "name": "osm:osm_simple_dark",
                "opacity": 1,
                "title": "OSM Simple Dark",
                "type": "wms",
                "url": [
                    "https://maps6.geosolutionsgroup.com/geoserver/wms",
                    "https://maps3.geosolutionsgroup.com/geoserver/wms",
                    "https://maps1.geosolutionsgroup.com/geoserver/wms",
                    "https://maps4.geosolutionsgroup.com/geoserver/wms",
                    "https://maps2.geosolutionsgroup.com/geoserver/wms",
                    "https://maps5.geosolutionsgroup.com/geoserver/wms"
                ],
                "visibility": false,
                "singleTile": false,
                "dimensions": [],
                "hideLoading": false,
                "handleClickOnLayer": false,
                "useForElevation": false,
                "hidden": false,
                "credits": {
                    "title": "OSM Simple Dark | Rendering <a href=\"https://www.geo-solutions.it/\">GeoSolutions</a> | Data © <a href=\"http://www.openstreetmap.org/\">OpenStreetMap</a> contributors, <a href=\"http://www.openstreetmap.org/copyright\">ODbL</a>"
                }
            },
            {
                "id": "osm:osm_simple_light__2",
                "format": "image/jpeg",
                "thumbURL": "assets/img/osm-simple-light.jpeg",
                "group": "background",
                "source": "osm_simple_light",
                "name": "osm:osm_simple_light",
                "opacity": 1,
                "title": "OSM Simple Light",
                "type": "wms",
                "url": [
                    "https://maps1.geosolutionsgroup.com/geoserver/wms",
                    "https://maps2.geosolutionsgroup.com/geoserver/wms",
                    "https://maps3.geosolutionsgroup.com/geoserver/wms",
                    "https://maps4.geosolutionsgroup.com/geoserver/wms",
                    "https://maps5.geosolutionsgroup.com/geoserver/wms",
                    "https://maps6.geosolutionsgroup.com/geoserver/wms"
                ],
                "visibility": false,
                "singleTile": false,
                "dimensions": [],
                "hideLoading": false,
                "handleClickOnLayer": false,
                "useForElevation": false,
                "hidden": false,
                "credits": {
                    "title": "OSM Simple Light | Rendering <a href=\"https://www.geo-solutions.it/\">GeoSolutions</a> | Data © <a href=\"http://www.openstreetmap.org/\">OpenStreetMap</a> contributors, <a href=\"http://www.openstreetmap.org/copyright\">ODbL</a>"
                }
            },
            {
                "id": "s2cloudless:s2cloudless__3",
                "format": "image/jpeg",
                "thumbURL": "assets/img/s2cloudless.jpeg",
                "group": "background",
                "source": "s2cloudless",
                "name": "s2cloudless:s2cloudless",
                "opacity": 1,
                "title": "Sentinel 2 Cloudless",
                "type": "wms",
                "url": [
                    "https://maps1.geosolutionsgroup.com/geoserver/wms",
                    "https://maps2.geosolutionsgroup.com/geoserver/wms",
                    "https://maps3.geosolutionsgroup.com/geoserver/wms",
                    "https://maps4.geosolutionsgroup.com/geoserver/wms",
                    "https://maps5.geosolutionsgroup.com/geoserver/wms",
                    "https://maps6.geosolutionsgroup.com/geoserver/wms"
                ],
                "visibility": false,
                "singleTile": false,
                "dimensions": [],
                "hideLoading": false,
                "handleClickOnLayer": false,
                "useForElevation": false,
                "hidden": false,
                "credits": {
                    "title": "<a class=\"a-light\" xmlns:dct=\"http://purl.org/dc/terms/\" href=\"https://s2maps.eu\" property=\"dct:title\">Sentinel-2 cloudless 2016</a> by <a class=\"a-light\" xmlns:cc=\"http://creativecommons.org/ns#\" href=\"https://eox.at\" property=\"cc:attributionName\" rel=\"cc:attributionURL\">EOX IT Services GmbH</a>"
                }
            },
            {
                "id": "mapnik__4",
                "group": "background",
                "source": "osm",
                "name": "mapnik",
                "title": "Open Street Map",
                "type": "osm",
                "visibility": false,
                "singleTile": false,
                "dimensions": [],
                "hideLoading": false,
                "handleClickOnLayer": false,
                "useForElevation": false,
                "hidden": false
            },
            {
                "id": "Night2012__5",
                "group": "background",
                "source": "nasagibs",
                "name": "Night2012",
                "provider": "NASAGIBS.ViirsEarthAtNight2012",
                "title": "NASAGIBS Night 2012",
                "type": "tileprovider",
                "visibility": false,
                "singleTile": false,
                "dimensions": [],
                "hideLoading": false,
                "handleClickOnLayer": false,
                "useForElevation": false,
                "hidden": false
            },
            {
                "id": "OpenTopoMap__6",
                "group": "background",
                "source": "OpenTopoMap",
                "name": "OpenTopoMap",
                "provider": "OpenTopoMap",
                "title": "OpenTopoMap",
                "type": "tileprovider",
                "visibility": false,
                "singleTile": false,
                "dimensions": [],
                "hideLoading": false,
                "handleClickOnLayer": false,
                "useForElevation": false,
                "hidden": false
            },
            {
                "id": "undefined__7",
                "group": "background",
                "source": "ol",
                "title": "Empty Background",
                "type": "empty",
                "visibility": false,
                "singleTile": false,
                "dimensions": [],
                "hideLoading": false,
                "handleClickOnLayer": false,
                "useForElevation": false,
                "hidden": false
            },
            {
                "id": "gs:observatories__9",
                "format": "image/png",
                "search": {
                    "url": "https://gs-stable.geo-solutions.it/geoserver/wfs",
                    "type": "wfs"
                },
                "name": "gs:observatories",
                "description": "",
                "availableStyles": [
                    {
                        "TYPE_NAME": "WMS_1_3_0.Style",
                        "name": "gs:observatories",
                        "title": "gs:observatories",
                        "legendURL": [
                            {
                                "TYPE_NAME": "WMS_1_3_0.LegendURL",
                                "width": 20,
                                "height": 20,
                                "format": "image/png",
                                "onlineResource": {
                                    "TYPE_NAME": "WMS_1_3_0.OnlineResource",
                                    "type": "simple",
                                    "href": "https://gs-stable.geo-solutions.it/geoserver/gs/observatories/ows?service=WMS&request=GetLegendGraphic&format=image%2Fpng&width=20&height=20&layer=observatories"
                                }
                            }
                        ]
                    },
                    {
                        "TYPE_NAME": "WMS_1_3_0.Style",
                        "name": "gs:base_sld___ef38abf0-4988-11ea-9973-87057b24c810",
                        "title": "Base SLD",
                        "legendURL": [
                            {
                                "TYPE_NAME": "WMS_1_3_0.LegendURL",
                                "width": 20,
                                "height": 20,
                                "format": "image/png",
                                "onlineResource": {
                                    "TYPE_NAME": "WMS_1_3_0.OnlineResource",
                                    "type": "simple",
                                    "href": "https://gs-stable.geo-solutions.it/geoserver/gs/observatories/ows?service=WMS&request=GetLegendGraphic&format=image%2Fpng&width=20&height=20&layer=observatories&style=base_sld___ef38abf0-4988-11ea-9973-87057b24c810"
                                }
                            }
                        ]
                    },
                    {
                        "TYPE_NAME": "WMS_1_3_0.Style",
                        "name": "gs:base_sld___c85deff0-498c-11ea-9973-87057b24c810",
                        "title": "Base SLD",
                        "legendURL": [
                            {
                                "TYPE_NAME": "WMS_1_3_0.LegendURL",
                                "width": 20,
                                "height": 20,
                                "format": "image/png",
                                "onlineResource": {
                                    "TYPE_NAME": "WMS_1_3_0.OnlineResource",
                                    "type": "simple",
                                    "href": "https://gs-stable.geo-solutions.it/geoserver/gs/observatories/ows?service=WMS&request=GetLegendGraphic&format=image%2Fpng&width=20&height=20&layer=observatories&style=base_sld___c85deff0-498c-11ea-9973-87057b24c810"
                                }
                            }
                        ]
                    }
                ],
                "layerFilter": {
                    "searchUrl": null,
                    "featureTypeConfigUrl": null,
                    "showGeneratedFilter": false,
                    "attributePanelExpanded": true,
                    "spatialPanelExpanded": true,
                    "crossLayerExpanded": true,
                    "showDetailsPanel": false,
                    "groupLevels": 5,
                    "useMapProjection": false,
                    "toolbarEnabled": true,
                    "groupFields": [
                        {
                            "id": 1,
                            "logic": "NOR",
                            "index": 0
                        }
                    ],
                    "maxFeaturesWPS": 5,
                    "filterFields": [
                        {
                            "rowId": 1629879859653,
                            "groupId": 1,
                            "attribute": "Type",
                            "operator": "=",
                            "value": "vvvvv",
                            "type": "string",
                            "fieldOptions": {
                                "valuesCount": 0,
                                "currentPage": 1
                            },
                            "exception": null,
                            "loading": false,
                            "openAutocompleteMenu": false,
                            "options": {
                                "Type": []
                            }
                        }
                    ],
                    "spatialField": {
                        "method": null,
                        "operation": "INTERSECTS",
                        "geometry": null,
                        "attribute": "the_geom"
                    },
                    "simpleFilterFields": [],
                    "crossLayerFilter": null,
                    "autocompleteEnabled": true
                },
                "title": "observatories",
                "type": "wms",
                "url": "https://gs-stable.geo-solutions.it/geoserver/wms",
                "bbox": {
                    "crs": "EPSG:4326",
                    "bounds": {
                        "minx": "-156.2575",
                        "miny": "-90.0",
                        "maxx": "123.33333333333333",
                        "maxy": "46.5475"
                    }
                },
                "visibility": true,
                "singleTile": false,
                "allowedSRS": {
                    "EPSG:3857": true,
                    "EPSG:900913": true,
                    "EPSG:4326": true
                },
                "dimensions": [],
                "hideLoading": false,
                "handleClickOnLayer": false,
                "catalogURL": null,
                "useForElevation": false,
                "hidden": false,
                "version": "1.3.0",
                "params": {}
            }
        ],
        "groups": [
            {
                "id": "Default",
                "title": "Default",
                "expanded": true
            }
        ],
        "backgrounds": [],
        "bookmark_search_config": {}
    },
    "catalogServices": {
        "services": {
            "gs_stable_csw": {
                "url": "https://gs-stable.geo-solutions.it/geoserver/csw",
                "type": "csw",
                "title": "GeoSolutions GeoServer CSW",
                "autoload": true
            },
            "gs_stable_wmts": {
                "url": "https://gs-stable.geo-solutions.it/geoserver/gwc/service/wmts",
                "type": "wmts",
                "title": "GeoSolutions GeoServer WMTS",
                "autoload": false
            },
            "gs_stable_wms": {
                "url": "https://gs-stable.geo-solutions.it/geoserver/wms",
                "type": "wms",
                "title": "GeoSolutions GeoServer WMS",
                "autoload": false,
                "showAdvancedSettings": false,
                "showTemplate": false,
                "hideThumbnail": false,
                "metadataTemplate": "<p>${description}</p>"
            },
            "gs_stable_wfs": {
                "url": "https://gs-stable.geo-solutions.it/geoserver/wfs",
                "type": "wfs",
                "title": "GeoSolutions GeoServer WFS",
                "autoload": false,
                "showAdvancedSettings": false,
                "showTemplate": false,
                "hideThumbnail": false,
                "metadataTemplate": ""
            }
        },
        "selectedService": "gs_stable_wms"
    },
    "widgetsConfig": {
        "widgets": [
            {
                "id": "888e97e0-057d-11ec-97f9-cd79f415d032",
                "layer": {
                    "type": "wms",
                    "format": "image/png",
                    "url": "https://gs-stable.geo-solutions.it/geoserver/wms",
                    "visibility": true,
                    "dimensions": [],
                    "name": "gs:observatories",
                    "title": "observatories",
                    "description": "",
                    "bbox": {
                        "crs": "EPSG:4326",
                        "bounds": {
                            "minx": "-156.2575",
                            "miny": "-90.0",
                            "maxx": "123.33333333333333",
                            "maxy": "46.5475"
                        }
                    },
                    "links": [],
                    "params": {},
                    "allowedSRS": {
                        "EPSG:3857": true,
                        "EPSG:900913": true,
                        "EPSG:4326": true
                    },
                    "catalogURL": null,
                    "version": "1.3.0",
                    "imageFormats": [
                        {
                            "label": "image/png",
                            "value": "image/png"
                        },
                        {
                            "label": "image/png8",
                            "value": "image/png8"
                        },
                        {
                            "label": "image/jpeg",
                            "value": "image/jpeg"
                        },
                        {
                            "label": "image/vnd.jpeg-png",
                            "value": "image/vnd.jpeg-png"
                        },
                        {
                            "label": "image/vnd.jpeg-png8",
                            "value": "image/vnd.jpeg-png8"
                        },
                        {
                            "label": "image/gif",
                            "value": "image/gif"
                        }
                    ],
                    "infoFormats": [
                        "text/plain",
                        "text/html",
                        "application/json"
                    ],
                    "id": "gs:observatories__9",
                    "loading": false,
                    "search": {
                        "url": "https://gs-stable.geo-solutions.it/geoserver/wfs",
                        "type": "wfs"
                    },
                    "previousLoadingError": false,
                    "loadingError": false,
                    "capabilities": {
                        "TYPE_NAME": "WMS_1_3_0.Layer",
                        "queryable": true,
                        "opaque": false,
                        "name": "observatories",
                        "title": "observatories",
                        "_abstract": "",
                        "keywordList": {
                            "TYPE_NAME": "WMS_1_3_0.KeywordList",
                            "keyword": [
                                {
                                    "TYPE_NAME": "WMS_1_3_0.Keyword",
                                    "value": "features"
                                },
                                {
                                    "TYPE_NAME": "WMS_1_3_0.Keyword",
                                    "value": "observatories"
                                }
                            ]
                        },
                        "crs": [
                            "EPSG:4326",
                            "CRS:84"
                        ],
                        "exGeographicBoundingBox": {
                            "TYPE_NAME": "WMS_1_3_0.EXGeographicBoundingBox",
                            "westBoundLongitude": -156.2575,
                            "eastBoundLongitude": 123.33333333333333,
                            "southBoundLatitude": -90,
                            "northBoundLatitude": 46.5475
                        },
                        "boundingBox": [
                            {
                                "TYPE_NAME": "WMS_1_3_0.BoundingBox",
                                "crs": "CRS:84",
                                "minx": -156.2575,
                                "miny": -90,
                                "maxx": 123.33333333333333,
                                "maxy": 46.5475
                            },
                            {
                                "TYPE_NAME": "WMS_1_3_0.BoundingBox",
                                "crs": "EPSG:4326",
                                "minx": -90,
                                "miny": -156.2575,
                                "maxx": 46.5475,
                                "maxy": 123.33333333333333
                            }
                        ],
                        "style": [
                            {
                                "TYPE_NAME": "WMS_1_3_0.Style",
                                "name": "gs:observatories",
                                "title": "gs:observatories",
                                "legendURL": [
                                    {
                                        "TYPE_NAME": "WMS_1_3_0.LegendURL",
                                        "width": 20,
                                        "height": 20,
                                        "format": "image/png",
                                        "onlineResource": {
                                            "TYPE_NAME": "WMS_1_3_0.OnlineResource",
                                            "type": "simple",
                                            "href": "https://gs-stable.geo-solutions.it/geoserver/gs/observatories/ows?service=WMS&request=GetLegendGraphic&format=image%2Fpng&width=20&height=20&layer=observatories"
                                        }
                                    }
                                ]
                            },
                            {
                                "TYPE_NAME": "WMS_1_3_0.Style",
                                "name": "gs:base_sld___ef38abf0-4988-11ea-9973-87057b24c810",
                                "title": "Base SLD",
                                "legendURL": [
                                    {
                                        "TYPE_NAME": "WMS_1_3_0.LegendURL",
                                        "width": 20,
                                        "height": 20,
                                        "format": "image/png",
                                        "onlineResource": {
                                            "TYPE_NAME": "WMS_1_3_0.OnlineResource",
                                            "type": "simple",
                                            "href": "https://gs-stable.geo-solutions.it/geoserver/gs/observatories/ows?service=WMS&request=GetLegendGraphic&format=image%2Fpng&width=20&height=20&layer=observatories&style=base_sld___ef38abf0-4988-11ea-9973-87057b24c810"
                                        }
                                    }
                                ]
                            },
                            {
                                "TYPE_NAME": "WMS_1_3_0.Style",
                                "name": "gs:base_sld___c85deff0-498c-11ea-9973-87057b24c810",
                                "title": "Base SLD",
                                "legendURL": [
                                    {
                                        "TYPE_NAME": "WMS_1_3_0.LegendURL",
                                        "width": 20,
                                        "height": 20,
                                        "format": "image/png",
                                        "onlineResource": {
                                            "TYPE_NAME": "WMS_1_3_0.OnlineResource",
                                            "type": "simple",
                                            "href": "https://gs-stable.geo-solutions.it/geoserver/gs/observatories/ows?service=WMS&request=GetLegendGraphic&format=image%2Fpng&width=20&height=20&layer=observatories&style=base_sld___c85deff0-498c-11ea-9973-87057b24c810"
                                        }
                                    }
                                ]
                            }
                        ]
                    },
                    "capabilitiesLoading": null,
                    "availableStyles": [
                        {
                            "TYPE_NAME": "WMS_1_3_0.Style",
                            "name": "gs:observatories",
                            "title": "gs:observatories",
                            "legendURL": [
                                {
                                    "TYPE_NAME": "WMS_1_3_0.LegendURL",
                                    "width": 20,
                                    "height": 20,
                                    "format": "image/png",
                                    "onlineResource": {
                                        "TYPE_NAME": "WMS_1_3_0.OnlineResource",
                                        "type": "simple",
                                        "href": "https://gs-stable.geo-solutions.it/geoserver/gs/observatories/ows?service=WMS&request=GetLegendGraphic&format=image%2Fpng&width=20&height=20&layer=observatories"
                                    }
                                }
                            ]
                        },
                        {
                            "TYPE_NAME": "WMS_1_3_0.Style",
                            "name": "gs:base_sld___ef38abf0-4988-11ea-9973-87057b24c810",
                            "title": "Base SLD",
                            "legendURL": [
                                {
                                    "TYPE_NAME": "WMS_1_3_0.LegendURL",
                                    "width": 20,
                                    "height": 20,
                                    "format": "image/png",
                                    "onlineResource": {
                                        "TYPE_NAME": "WMS_1_3_0.OnlineResource",
                                        "type": "simple",
                                        "href": "https://gs-stable.geo-solutions.it/geoserver/gs/observatories/ows?service=WMS&request=GetLegendGraphic&format=image%2Fpng&width=20&height=20&layer=observatories&style=base_sld___ef38abf0-4988-11ea-9973-87057b24c810"
                                    }
                                }
                            ]
                        },
                        {
                            "TYPE_NAME": "WMS_1_3_0.Style",
                            "name": "gs:base_sld___c85deff0-498c-11ea-9973-87057b24c810",
                            "title": "Base SLD",
                            "legendURL": [
                                {
                                    "TYPE_NAME": "WMS_1_3_0.LegendURL",
                                    "width": 20,
                                    "height": 20,
                                    "format": "image/png",
                                    "onlineResource": {
                                        "TYPE_NAME": "WMS_1_3_0.OnlineResource",
                                        "type": "simple",
                                        "href": "https://gs-stable.geo-solutions.it/geoserver/gs/observatories/ows?service=WMS&request=GetLegendGraphic&format=image%2Fpng&width=20&height=20&layer=observatories&style=base_sld___c85deff0-498c-11ea-9973-87057b24c810"
                                    }
                                }
                            ]
                        }
                    ],
                    "layerFilter": {
                        "searchUrl": null,
                        "featureTypeConfigUrl": null,
                        "showGeneratedFilter": false,
                        "attributePanelExpanded": true,
                        "spatialPanelExpanded": true,
                        "crossLayerExpanded": true,
                        "showDetailsPanel": false,
                        "groupLevels": 5,
                        "useMapProjection": false,
                        "toolbarEnabled": true,
                        "groupFields": [
                            {
                                "id": 1,
                                "logic": "NOR",
                                "index": 0
                            }
                        ],
                        "maxFeaturesWPS": 5,
                        "filterFields": [
                            {
                                "rowId": 1629879859653,
                                "groupId": 1,
                                "attribute": "Type",
                                "operator": "=",
                                "value": "vvvvv",
                                "type": "string",
                                "fieldOptions": {
                                    "valuesCount": 0,
                                    "currentPage": 1
                                },
                                "exception": null,
                                "loading": false,
                                "openAutocompleteMenu": false,
                                "options": {
                                    "Type": []
                                }
                            }
                        ],
                        "spatialField": {
                            "method": null,
                            "operation": "INTERSECTS",
                            "geometry": null,
                            "attribute": "the_geom"
                        },
                        "simpleFilterFields": [],
                        "crossLayerFilter": null,
                        "autocompleteEnabled": true
                    }
                },
                "url": "https://gs-stable.geo-solutions.it/geoserver/wms",
                "legend": false,
                "mapSync": true,
                "cartesian": true,
                "yAxis": true,
                "type": "bar",
                "widgetType": "chart",
                "geomProp": "the_geom",
                "options": {
                    "groupByAttributes": "Type",
                    "aggregationAttribute": "Elev_m",
                    "aggregateFunction": "Average"
                },
                "autoColorOptions": {
                    "base": 190,
                    "range": 20,
                    "name": "global.colors.blue"
                },
                "panel": false,
                "title": "Average elevation by type",
                "description": "Average elevation by observatory types",
                "dataGrid": {
                    "y": 0,
                    "x": 0,
                    "w": 1,
                    "h": 1
                },
                "filter": {
                    "featureTypeName": "gs:observatories",
                    "groupFields": [
                        {
                            "id": 1,
                            "logic": "NOR",
                            "index": 0
                        }
                    ],
                    "filterFields": [
                        {
                            "rowId": 1629879819614,
                            "groupId": 1,
                            "attribute": "Type",
                            "operator": "=",
                            "value": "vvvvv",
                            "type": "string",
                            "fieldOptions": {
                                "valuesCount": 0,
                                "currentPage": 1
                            },
                            "exception": null,
                            "loading": false,
                            "options": {
                                "Type": []
                            },
                            "openAutocompleteMenu": false
                        }
                    ],
                    "spatialField": {
                        "method": null,
                        "operation": "INTERSECTS",
                        "geometry": null,
                        "attribute": "the_geom"
                    },
                    "pagination": null,
                    "filterType": "OGC",
                    "ogcVersion": "1.1.0",
                    "sortOptions": null,
                    "crossLayerFilter": null,
                    "hits": false
                }
            },
            {
                "id": "f06e15c0-057d-11ec-97f9-cd79f415d032",
                "layer": {
                    "type": "wms",
                    "format": "image/png",
                    "url": "https://gs-stable.geo-solutions.it/geoserver/wms",
                    "visibility": true,
                    "dimensions": [],
                    "name": "gs:observatories",
                    "title": "observatories",
                    "description": "",
                    "bbox": {
                        "crs": "EPSG:4326",
                        "bounds": {
                            "minx": "-156.2575",
                            "miny": "-90.0",
                            "maxx": "123.33333333333333",
                            "maxy": "46.5475"
                        }
                    },
                    "links": [],
                    "params": {},
                    "allowedSRS": {
                        "EPSG:3857": true,
                        "EPSG:900913": true,
                        "EPSG:4326": true
                    },
                    "catalogURL": null,
                    "version": "1.3.0",
                    "imageFormats": [
                        {
                            "label": "image/png",
                            "value": "image/png"
                        },
                        {
                            "label": "image/png8",
                            "value": "image/png8"
                        },
                        {
                            "label": "image/jpeg",
                            "value": "image/jpeg"
                        },
                        {
                            "label": "image/vnd.jpeg-png",
                            "value": "image/vnd.jpeg-png"
                        },
                        {
                            "label": "image/vnd.jpeg-png8",
                            "value": "image/vnd.jpeg-png8"
                        },
                        {
                            "label": "image/gif",
                            "value": "image/gif"
                        }
                    ],
                    "infoFormats": [
                        "text/plain",
                        "text/html",
                        "application/json"
                    ],
                    "id": "gs:observatories__9",
                    "loading": false,
                    "search": {
                        "url": "https://gs-stable.geo-solutions.it/geoserver/wfs",
                        "type": "wfs"
                    },
                    "previousLoadingError": false,
                    "loadingError": false,
                    "capabilities": {
                        "TYPE_NAME": "WMS_1_3_0.Layer",
                        "queryable": true,
                        "opaque": false,
                        "name": "observatories",
                        "title": "observatories",
                        "_abstract": "",
                        "keywordList": {
                            "TYPE_NAME": "WMS_1_3_0.KeywordList",
                            "keyword": [
                                {
                                    "TYPE_NAME": "WMS_1_3_0.Keyword",
                                    "value": "features"
                                },
                                {
                                    "TYPE_NAME": "WMS_1_3_0.Keyword",
                                    "value": "observatories"
                                }
                            ]
                        },
                        "crs": [
                            "EPSG:4326",
                            "CRS:84"
                        ],
                        "exGeographicBoundingBox": {
                            "TYPE_NAME": "WMS_1_3_0.EXGeographicBoundingBox",
                            "westBoundLongitude": -156.2575,
                            "eastBoundLongitude": 123.33333333333333,
                            "southBoundLatitude": -90,
                            "northBoundLatitude": 46.5475
                        },
                        "boundingBox": [
                            {
                                "TYPE_NAME": "WMS_1_3_0.BoundingBox",
                                "crs": "CRS:84",
                                "minx": -156.2575,
                                "miny": -90,
                                "maxx": 123.33333333333333,
                                "maxy": 46.5475
                            },
                            {
                                "TYPE_NAME": "WMS_1_3_0.BoundingBox",
                                "crs": "EPSG:4326",
                                "minx": -90,
                                "miny": -156.2575,
                                "maxx": 46.5475,
                                "maxy": 123.33333333333333
                            }
                        ],
                        "style": [
                            {
                                "TYPE_NAME": "WMS_1_3_0.Style",
                                "name": "gs:observatories",
                                "title": "gs:observatories",
                                "legendURL": [
                                    {
                                        "TYPE_NAME": "WMS_1_3_0.LegendURL",
                                        "width": 20,
                                        "height": 20,
                                        "format": "image/png",
                                        "onlineResource": {
                                            "TYPE_NAME": "WMS_1_3_0.OnlineResource",
                                            "type": "simple",
                                            "href": "https://gs-stable.geo-solutions.it/geoserver/gs/observatories/ows?service=WMS&request=GetLegendGraphic&format=image%2Fpng&width=20&height=20&layer=observatories"
                                        }
                                    }
                                ]
                            },
                            {
                                "TYPE_NAME": "WMS_1_3_0.Style",
                                "name": "gs:base_sld___ef38abf0-4988-11ea-9973-87057b24c810",
                                "title": "Base SLD",
                                "legendURL": [
                                    {
                                        "TYPE_NAME": "WMS_1_3_0.LegendURL",
                                        "width": 20,
                                        "height": 20,
                                        "format": "image/png",
                                        "onlineResource": {
                                            "TYPE_NAME": "WMS_1_3_0.OnlineResource",
                                            "type": "simple",
                                            "href": "https://gs-stable.geo-solutions.it/geoserver/gs/observatories/ows?service=WMS&request=GetLegendGraphic&format=image%2Fpng&width=20&height=20&layer=observatories&style=base_sld___ef38abf0-4988-11ea-9973-87057b24c810"
                                        }
                                    }
                                ]
                            },
                            {
                                "TYPE_NAME": "WMS_1_3_0.Style",
                                "name": "gs:base_sld___c85deff0-498c-11ea-9973-87057b24c810",
                                "title": "Base SLD",
                                "legendURL": [
                                    {
                                        "TYPE_NAME": "WMS_1_3_0.LegendURL",
                                        "width": 20,
                                        "height": 20,
                                        "format": "image/png",
                                        "onlineResource": {
                                            "TYPE_NAME": "WMS_1_3_0.OnlineResource",
                                            "type": "simple",
                                            "href": "https://gs-stable.geo-solutions.it/geoserver/gs/observatories/ows?service=WMS&request=GetLegendGraphic&format=image%2Fpng&width=20&height=20&layer=observatories&style=base_sld___c85deff0-498c-11ea-9973-87057b24c810"
                                        }
                                    }
                                ]
                            }
                        ]
                    },
                    "capabilitiesLoading": null,
                    "availableStyles": [
                        {
                            "TYPE_NAME": "WMS_1_3_0.Style",
                            "name": "gs:observatories",
                            "title": "gs:observatories",
                            "legendURL": [
                                {
                                    "TYPE_NAME": "WMS_1_3_0.LegendURL",
                                    "width": 20,
                                    "height": 20,
                                    "format": "image/png",
                                    "onlineResource": {
                                        "TYPE_NAME": "WMS_1_3_0.OnlineResource",
                                        "type": "simple",
                                        "href": "https://gs-stable.geo-solutions.it/geoserver/gs/observatories/ows?service=WMS&request=GetLegendGraphic&format=image%2Fpng&width=20&height=20&layer=observatories"
                                    }
                                }
                            ]
                        },
                        {
                            "TYPE_NAME": "WMS_1_3_0.Style",
                            "name": "gs:base_sld___ef38abf0-4988-11ea-9973-87057b24c810",
                            "title": "Base SLD",
                            "legendURL": [
                                {
                                    "TYPE_NAME": "WMS_1_3_0.LegendURL",
                                    "width": 20,
                                    "height": 20,
                                    "format": "image/png",
                                    "onlineResource": {
                                        "TYPE_NAME": "WMS_1_3_0.OnlineResource",
                                        "type": "simple",
                                        "href": "https://gs-stable.geo-solutions.it/geoserver/gs/observatories/ows?service=WMS&request=GetLegendGraphic&format=image%2Fpng&width=20&height=20&layer=observatories&style=base_sld___ef38abf0-4988-11ea-9973-87057b24c810"
                                    }
                                }
                            ]
                        },
                        {
                            "TYPE_NAME": "WMS_1_3_0.Style",
                            "name": "gs:base_sld___c85deff0-498c-11ea-9973-87057b24c810",
                            "title": "Base SLD",
                            "legendURL": [
                                {
                                    "TYPE_NAME": "WMS_1_3_0.LegendURL",
                                    "width": 20,
                                    "height": 20,
                                    "format": "image/png",
                                    "onlineResource": {
                                        "TYPE_NAME": "WMS_1_3_0.OnlineResource",
                                        "type": "simple",
                                        "href": "https://gs-stable.geo-solutions.it/geoserver/gs/observatories/ows?service=WMS&request=GetLegendGraphic&format=image%2Fpng&width=20&height=20&layer=observatories&style=base_sld___c85deff0-498c-11ea-9973-87057b24c810"
                                    }
                                }
                            ]
                        }
                    ],
                    "layerFilter": {
                        "searchUrl": null,
                        "featureTypeConfigUrl": null,
                        "showGeneratedFilter": false,
                        "attributePanelExpanded": true,
                        "spatialPanelExpanded": true,
                        "crossLayerExpanded": true,
                        "showDetailsPanel": false,
                        "groupLevels": 5,
                        "useMapProjection": false,
                        "toolbarEnabled": true,
                        "groupFields": [
                            {
                                "id": 1,
                                "logic": "NOR",
                                "index": 0
                            }
                        ],
                        "maxFeaturesWPS": 5,
                        "filterFields": [
                            {
                                "rowId": 1629879859653,
                                "groupId": 1,
                                "attribute": "Type",
                                "operator": "=",
                                "value": "vvvvv",
                                "type": "string",
                                "fieldOptions": {
                                    "valuesCount": 0,
                                    "currentPage": 1
                                },
                                "exception": null,
                                "loading": false,
                                "openAutocompleteMenu": false,
                                "options": {
                                    "Type": []
                                }
                            }
                        ],
                        "spatialField": {
                            "method": null,
                            "operation": "INTERSECTS",
                            "geometry": null,
                            "attribute": "the_geom"
                        },
                        "simpleFilterFields": [],
                        "crossLayerFilter": null,
                        "autocompleteEnabled": true
                    }
                },
                "url": "https://gs-stable.geo-solutions.it/geoserver/wms",
                "legend": false,
                "mapSync": true,
                "cartesian": true,
                "yAxis": true,
                "widgetType": "table",
                "geomProp": "the_geom",
                "options": {
                    "propertyName": [
                        "Type",
                        "Observator",
                        "Elev_m"
                    ]
                },
                "title": "Elevations",
                "dataGrid": {
                    "y": 0,
                    "x": 0,
                    "w": 1,
                    "h": 1
                }
            },
            {
                "id": "5e683ab0-057e-11ec-97f9-cd79f415d032",
                "layer": {
                    "type": "wms",
                    "format": "image/png",
                    "url": "https://gs-stable.geo-solutions.it/geoserver/wms",
                    "visibility": true,
                    "dimensions": [],
                    "name": "gs:observatories",
                    "title": "observatories",
                    "description": "",
                    "bbox": {
                        "crs": "EPSG:4326",
                        "bounds": {
                            "minx": "-156.2575",
                            "miny": "-90.0",
                            "maxx": "123.33333333333333",
                            "maxy": "46.5475"
                        }
                    },
                    "links": [],
                    "params": {},
                    "allowedSRS": {
                        "EPSG:3857": true,
                        "EPSG:900913": true,
                        "EPSG:4326": true
                    },
                    "catalogURL": null,
                    "version": "1.3.0",
                    "imageFormats": [
                        {
                            "label": "image/png",
                            "value": "image/png"
                        },
                        {
                            "label": "image/png8",
                            "value": "image/png8"
                        },
                        {
                            "label": "image/jpeg",
                            "value": "image/jpeg"
                        },
                        {
                            "label": "image/vnd.jpeg-png",
                            "value": "image/vnd.jpeg-png"
                        },
                        {
                            "label": "image/vnd.jpeg-png8",
                            "value": "image/vnd.jpeg-png8"
                        },
                        {
                            "label": "image/gif",
                            "value": "image/gif"
                        }
                    ],
                    "infoFormats": [
                        "text/plain",
                        "text/html",
                        "application/json"
                    ],
                    "id": "gs:observatories__9",
                    "loading": false,
                    "search": {
                        "url": "https://gs-stable.geo-solutions.it/geoserver/wfs",
                        "type": "wfs"
                    },
                    "previousLoadingError": false,
                    "loadingError": false,
                    "capabilities": {
                        "TYPE_NAME": "WMS_1_3_0.Layer",
                        "queryable": true,
                        "opaque": false,
                        "name": "observatories",
                        "title": "observatories",
                        "_abstract": "",
                        "keywordList": {
                            "TYPE_NAME": "WMS_1_3_0.KeywordList",
                            "keyword": [
                                {
                                    "TYPE_NAME": "WMS_1_3_0.Keyword",
                                    "value": "features"
                                },
                                {
                                    "TYPE_NAME": "WMS_1_3_0.Keyword",
                                    "value": "observatories"
                                }
                            ]
                        },
                        "crs": [
                            "EPSG:4326",
                            "CRS:84"
                        ],
                        "exGeographicBoundingBox": {
                            "TYPE_NAME": "WMS_1_3_0.EXGeographicBoundingBox",
                            "westBoundLongitude": -156.2575,
                            "eastBoundLongitude": 123.33333333333333,
                            "southBoundLatitude": -90,
                            "northBoundLatitude": 46.5475
                        },
                        "boundingBox": [
                            {
                                "TYPE_NAME": "WMS_1_3_0.BoundingBox",
                                "crs": "CRS:84",
                                "minx": -156.2575,
                                "miny": -90,
                                "maxx": 123.33333333333333,
                                "maxy": 46.5475
                            },
                            {
                                "TYPE_NAME": "WMS_1_3_0.BoundingBox",
                                "crs": "EPSG:4326",
                                "minx": -90,
                                "miny": -156.2575,
                                "maxx": 46.5475,
                                "maxy": 123.33333333333333
                            }
                        ],
                        "style": [
                            {
                                "TYPE_NAME": "WMS_1_3_0.Style",
                                "name": "gs:observatories",
                                "title": "gs:observatories",
                                "legendURL": [
                                    {
                                        "TYPE_NAME": "WMS_1_3_0.LegendURL",
                                        "width": 20,
                                        "height": 20,
                                        "format": "image/png",
                                        "onlineResource": {
                                            "TYPE_NAME": "WMS_1_3_0.OnlineResource",
                                            "type": "simple",
                                            "href": "https://gs-stable.geo-solutions.it/geoserver/gs/observatories/ows?service=WMS&request=GetLegendGraphic&format=image%2Fpng&width=20&height=20&layer=observatories"
                                        }
                                    }
                                ]
                            },
                            {
                                "TYPE_NAME": "WMS_1_3_0.Style",
                                "name": "gs:base_sld___ef38abf0-4988-11ea-9973-87057b24c810",
                                "title": "Base SLD",
                                "legendURL": [
                                    {
                                        "TYPE_NAME": "WMS_1_3_0.LegendURL",
                                        "width": 20,
                                        "height": 20,
                                        "format": "image/png",
                                        "onlineResource": {
                                            "TYPE_NAME": "WMS_1_3_0.OnlineResource",
                                            "type": "simple",
                                            "href": "https://gs-stable.geo-solutions.it/geoserver/gs/observatories/ows?service=WMS&request=GetLegendGraphic&format=image%2Fpng&width=20&height=20&layer=observatories&style=base_sld___ef38abf0-4988-11ea-9973-87057b24c810"
                                        }
                                    }
                                ]
                            },
                            {
                                "TYPE_NAME": "WMS_1_3_0.Style",
                                "name": "gs:base_sld___c85deff0-498c-11ea-9973-87057b24c810",
                                "title": "Base SLD",
                                "legendURL": [
                                    {
                                        "TYPE_NAME": "WMS_1_3_0.LegendURL",
                                        "width": 20,
                                        "height": 20,
                                        "format": "image/png",
                                        "onlineResource": {
                                            "TYPE_NAME": "WMS_1_3_0.OnlineResource",
                                            "type": "simple",
                                            "href": "https://gs-stable.geo-solutions.it/geoserver/gs/observatories/ows?service=WMS&request=GetLegendGraphic&format=image%2Fpng&width=20&height=20&layer=observatories&style=base_sld___c85deff0-498c-11ea-9973-87057b24c810"
                                        }
                                    }
                                ]
                            }
                        ]
                    },
                    "capabilitiesLoading": null,
                    "availableStyles": [
                        {
                            "TYPE_NAME": "WMS_1_3_0.Style",
                            "name": "gs:observatories",
                            "title": "gs:observatories",
                            "legendURL": [
                                {
                                    "TYPE_NAME": "WMS_1_3_0.LegendURL",
                                    "width": 20,
                                    "height": 20,
                                    "format": "image/png",
                                    "onlineResource": {
                                        "TYPE_NAME": "WMS_1_3_0.OnlineResource",
                                        "type": "simple",
                                        "href": "https://gs-stable.geo-solutions.it/geoserver/gs/observatories/ows?service=WMS&request=GetLegendGraphic&format=image%2Fpng&width=20&height=20&layer=observatories"
                                    }
                                }
                            ]
                        },
                        {
                            "TYPE_NAME": "WMS_1_3_0.Style",
                            "name": "gs:base_sld___ef38abf0-4988-11ea-9973-87057b24c810",
                            "title": "Base SLD",
                            "legendURL": [
                                {
                                    "TYPE_NAME": "WMS_1_3_0.LegendURL",
                                    "width": 20,
                                    "height": 20,
                                    "format": "image/png",
                                    "onlineResource": {
                                        "TYPE_NAME": "WMS_1_3_0.OnlineResource",
                                        "type": "simple",
                                        "href": "https://gs-stable.geo-solutions.it/geoserver/gs/observatories/ows?service=WMS&request=GetLegendGraphic&format=image%2Fpng&width=20&height=20&layer=observatories&style=base_sld___ef38abf0-4988-11ea-9973-87057b24c810"
                                    }
                                }
                            ]
                        },
                        {
                            "TYPE_NAME": "WMS_1_3_0.Style",
                            "name": "gs:base_sld___c85deff0-498c-11ea-9973-87057b24c810",
                            "title": "Base SLD",
                            "legendURL": [
                                {
                                    "TYPE_NAME": "WMS_1_3_0.LegendURL",
                                    "width": 20,
                                    "height": 20,
                                    "format": "image/png",
                                    "onlineResource": {
                                        "TYPE_NAME": "WMS_1_3_0.OnlineResource",
                                        "type": "simple",
                                        "href": "https://gs-stable.geo-solutions.it/geoserver/gs/observatories/ows?service=WMS&request=GetLegendGraphic&format=image%2Fpng&width=20&height=20&layer=observatories&style=base_sld___c85deff0-498c-11ea-9973-87057b24c810"
                                    }
                                }
                            ]
                        }
                    ],
                    "layerFilter": {
                        "searchUrl": null,
                        "featureTypeConfigUrl": null,
                        "showGeneratedFilter": false,
                        "attributePanelExpanded": true,
                        "spatialPanelExpanded": true,
                        "crossLayerExpanded": true,
                        "showDetailsPanel": false,
                        "groupLevels": 5,
                        "useMapProjection": false,
                        "toolbarEnabled": true,
                        "groupFields": [
                            {
                                "id": 1,
                                "logic": "NOR",
                                "index": 0
                            }
                        ],
                        "maxFeaturesWPS": 5,
                        "filterFields": [
                            {
                                "rowId": 1629879859653,
                                "groupId": 1,
                                "attribute": "Type",
                                "operator": "=",
                                "value": "vvvvv",
                                "type": "string",
                                "fieldOptions": {
                                    "valuesCount": 0,
                                    "currentPage": 1
                                },
                                "exception": null,
                                "loading": false,
                                "openAutocompleteMenu": false,
                                "options": {
                                    "Type": []
                                }
                            }
                        ],
                        "spatialField": {
                            "method": null,
                            "operation": "INTERSECTS",
                            "geometry": null,
                            "attribute": "the_geom"
                        },
                        "simpleFilterFields": [],
                        "crossLayerFilter": null,
                        "autocompleteEnabled": true
                    }
                },
                "url": "https://gs-stable.geo-solutions.it/geoserver/wms",
                "legend": false,
                "mapSync": true,
                "cartesian": true,
                "yAxis": true,
                "widgetType": "counter",
                "geomProp": "the_geom",
                "options": {
                    "aggregationAttribute": "Elev_m",
                    "aggregateFunction": "Max",
                    "seriesOptions": [
                        {
                            "uom": " m"
                        }
                    ]
                },
                "title": "Max elevation of observatories in view",
                "dataGrid": {
                    "y": 0,
                    "x": 0,
                    "w": 1,
                    "h": 1
                }
            }
        ],
        "layouts": {
            "xxs": [
                {
                    "w": 1,
                    "h": 1,
                    "x": 0,
                    "y": 0,
                    "i": "888e97e0-057d-11ec-97f9-cd79f415d032",
                    "moved": false
                },
                {
                    "w": 1,
                    "h": 1,
                    "x": 0,
                    "y": 1,
                    "i": "f06e15c0-057d-11ec-97f9-cd79f415d032",
                    "moved": false
                },
                {
                    "w": 1,
                    "h": 1,
                    "x": 0,
                    "y": 2,
                    "i": "5e683ab0-057e-11ec-97f9-cd79f415d032",
                    "moved": false
                }
            ],
            "md": [
                {
                    "w": 2,
                    "h": 1,
                    "x": 4,
                    "y": 3,
                    "i": "888e97e0-057d-11ec-97f9-cd79f415d032",
                    "moved": false,
                    "static": false
                },
                {
                    "w": 2,
                    "h": 2,
                    "x": 4,
                    "y": 1,
                    "i": "f06e15c0-057d-11ec-97f9-cd79f415d032",
                    "moved": false,
                    "static": false
                },
                {
                    "w": 2,
                    "h": 1,
                    "x": 4,
                    "y": 0,
                    "i": "5e683ab0-057e-11ec-97f9-cd79f415d032",
                    "moved": false,
                    "static": false
                }
            ]
        }
    },
    "mapInfoConfiguration": {},
    "dimensionData": {},
    "timelineData": {}
}
